REACTColor/__init__.py
REACTColor/__main__.py
REACTColor-0.0.1.dist-info/LICENSE
REACTColor-0.0.1.dist-info/METADATA
REACTColor-0.0.1.dist-info/WHEEL
REACTColor-0.0.1.dist-info/entry_points.txt
REACTColor-0.0.1.dist-info/top_level.txt
REACTColor-0.0.1.dist-info/RECORD
