Metadata-Version: 2.1
Name: REACTColor
Version: 0.0.1
Summary: UNKNOWN
Home-page: UNKNOWN
Author: Saathvik Kannan
License: MIT
Platform: UNKNOWN
Classifier: License :: OSI Approved :: MIT License
Classifier: Programming Language :: Python :: 3
Classifier: Programming Language :: Python :: 3.7
License-File: LICENSE
Requires-Dist: pandas
Requires-Dist: matplotlib
Requires-Dist: Pillow
Requires-Dist: opencv-python
Requires-Dist: PySimpleGUIWeb
Requires-Dist: progress
